dc_texter/__init__.py
dc_texter/config.py
dc_texter/texter.py
dc_texter-0.1.5.dist-info/LICENSE.txt
dc_texter-0.1.5.dist-info/METADATA
dc_texter-0.1.5.dist-info/WHEEL
dc_texter-0.1.5.dist-info/top_level.txt
dc_texter-0.1.5.dist-info/RECORD
