Metadata-Version: 2.2
Name: dc_texter
Version: 0.1.5
Summary: A simple SMS text alert utility for Python projects
Author-email: Denise Case <denisecase@gmail.com>
License: MIT License
Project-URL: Homepage, https://github.com/denisecase/dc_texter
Project-URL: Repository, https://github.com/denisecase/dc_texter
Project-URL: BugTracker, https://github.com/denisecase/dc_texter/issues
Keywords: sms,text,alert,notification
Classifier: Intended Audience :: Developers
Classifier: License :: OSI Approved :: MIT License
Classifier: Programming Language :: Python :: 3.11
Classifier: Programming Language :: Python :: 3.12
Requires-Python: >=3.11
License-File: LICENSE.txt
Provides-Extra: dev
Requires-Dist: pytest; extra == "dev"
Requires-Dist: twine; extra == "dev"
Requires-Dist: build; extra == "dev"
